Metadata-Version: 1.0
Name: excelToPdf
Version: 0.0.2
Summary: A Package To Convert Excels to pdf. 
Home-page: UNKNOWN
Author: Suraj Kumar
Author-email: UNKNOWN
License: UNKNOWN
Platform: UNKNOWN
